awseasy/__init__.py
awseasy/ec2.py
awseasy-0.0.1.dist-info/METADATA
awseasy-0.0.1.dist-info/WHEEL
awseasy-0.0.1.dist-info/top_level.txt
awseasy-0.0.1.dist-info/RECORD
