Metadata-Version: 2.1
Name: awseasy
Version: 0.0.1
Summary: A package to simplify AWS usage
Home-page: 
Author: Byoungkwon An
Author-email: drancom@gmail.com
Classifier: Programming Language :: Python :: 3
Classifier: License :: OSI Approved :: MIT License
Classifier: Operating System :: OS Independent
Requires-Python: >=3.0
Requires-Dist: boto3
Requires-Dist: python-dotenv
